LICENSE
src/__init__.py
src/wildmatch/__init__.py
src/wildmatch/filter.py
wildmatch-0.3.3.dist-info/LICENSE
wildmatch-0.3.3.dist-info/METADATA
wildmatch-0.3.3.dist-info/WHEEL
wildmatch-0.3.3.dist-info/entry_points.txt
wildmatch-0.3.3.dist-info/RECORD
