Metadata-Version: 2.1
Name: wildmatch
Version: 0.3.3
Summary: Wrap pathspec (gitignore-like wildmatch) in a CLI
License: GPLv3
Keywords: git,gitignore,cli
Author: Emma Doyle
Author-email: emma@premiscale.com
Maintainer: Emma Doyle
Maintainer-email: emma@premiscale.com
Requires-Python: >=3.9,<4.0
Classifier: License :: Other/Proprietary License
Classifier: Programming Language :: Python :: 3
Classifier: Programming Language :: Python :: 3.9
Classifier: Programming Language :: Python :: 3.10
Classifier: Programming Language :: Python :: 3.11
Requires-Dist: pathspec (>=0.11.1,<0.12.0)
